Metadata-Version: 1.2
Name: ad-AHJZ
Version: 1.9
Summary: A Package that calculates Automatic Differentiation for both Scalar and Vector Inputs
Home-page: https://github.com/cs107-AHJZ/cs107-FinalProject.git
Author: Aditi Memani, Hari Raval, Joseph Zuccarelli, liuzongjun
License: UNKNOWN
Platform: UNKNOWN
Classifier: Programming Language :: Python :: 3
Classifier: Operating System :: OS Independent
Requires-Python: >=3.6
